Model_Trainer/Model_training.py
Model_Trainer/__init__.py
Model_Trainer/data_splitting.py
Model_Trainer-1.0.dist-info/LICENSE
Model_Trainer-1.0.dist-info/METADATA
Model_Trainer-1.0.dist-info/WHEEL
Model_Trainer-1.0.dist-info/top_level.txt
Model_Trainer-1.0.dist-info/RECORD
