Metadata-Version: 2.1
Name: Model-Trainer
Version: 1.0
Summary: Simplify YOLO model training and data splitting for object detection tasks.
Home-page: https://github.com/Rathoreatri03/Model_Trainer
Author: Atri Rathore
Author-email: <rathoreatri@gmail.com>
Keywords: python,model training,YOLO,data splitting,deep learning
Classifier: Development Status :: 1 - Planning
Classifier: Intended Audience :: Developers
Classifier: Programming Language :: Python :: 3
Classifier: Operating System :: Unix
Classifier: Operating System :: MacOS :: MacOS X
Classifier: Operating System :: Microsoft :: Windows
License-File: LICENSE
Requires-Dist: torch
Requires-Dist: ultralytics
